dbtsl/__about__.py
dbtsl/__init__.py
dbtsl/asyncio.py
dbtsl/backoff.py
dbtsl/env.py
dbtsl/error.py
dbtsl/py.typed
dbtsl/timeout.py
dbtsl/api/__init__.py
dbtsl/api/adbc/__init__.py
dbtsl/api/adbc/protocol.py
dbtsl/api/adbc/client/__init__.py
dbtsl/api/adbc/client/asyncio.py
dbtsl/api/adbc/client/base.py
dbtsl/api/adbc/client/sync.py
dbtsl/api/graphql/__init__.py
dbtsl/api/graphql/protocol.py
dbtsl/api/graphql/util.py
dbtsl/api/graphql/client/__init__.py
dbtsl/api/graphql/client/asyncio.py
dbtsl/api/graphql/client/asyncio.pyi
dbtsl/api/graphql/client/base.py
dbtsl/api/graphql/client/sync.py
dbtsl/api/graphql/client/sync.pyi
dbtsl/api/shared/__init__.py
dbtsl/api/shared/query_params.py
dbtsl/client/__init__.py
dbtsl/client/asyncio.py
dbtsl/client/asyncio.pyi
dbtsl/client/base.py
dbtsl/client/sync.py
dbtsl/client/sync.pyi
dbtsl/models/__init__.py
dbtsl/models/base.py
dbtsl/models/dimension.py
dbtsl/models/entity.py
dbtsl/models/environment.py
dbtsl/models/measure.py
dbtsl/models/metric.py
dbtsl/models/query.py
dbtsl/models/saved_query.py
dbtsl/models/time.py
dbt_sl_sdk-0.13.1.dist-info/METADATA
dbt_sl_sdk-0.13.1.dist-info/WHEEL
dbt_sl_sdk-0.13.1.dist-info/licenses/LICENSE
dbt_sl_sdk-0.13.1.dist-info/RECORD
