Metadata-Version: 2.3
Name: dbt-sl-sdk
Version: 0.13.1
Summary: A client for dbt's Semantic Layer
Author: dbt Labs
License-File: LICENSE
Requires-Python: <3.14,>=3.9
Requires-Dist: adbc-driver-flightsql>=0.11.0
Requires-Dist: adbc-driver-manager>=0.11.0
Requires-Dist: mashumaro<4.0,>=3.11
Requires-Dist: pyarrow>=12.0.0; python_version <= '3.11'
Requires-Dist: pyarrow>=14.0.0; python_version == '3.12'
Requires-Dist: pyarrow>=18.0.0; python_version >= '3.13'
Requires-Dist: typing-extensions<5.0.0,>=4.12.0; python_version >= '3.13'
Requires-Dist: typing-extensions<5.0.0,>=4.4.0; python_version <= '3.11'
Requires-Dist: typing-extensions<5.0.0,>=4.7.0; python_version == '3.12'
Provides-Extra: async
Requires-Dist: gql[aiohttp]<4.0.0,>=3.5.0; extra == 'async'
Provides-Extra: dev
Requires-Dist: basedpyright; extra == 'dev'
Requires-Dist: mypy; extra == 'dev'
Requires-Dist: pyarrow-stubs; extra == 'dev'
Requires-Dist: ruff; extra == 'dev'
Requires-Dist: uv; extra == 'dev'
Provides-Extra: sync
Requires-Dist: gql[requests]<4.0.0,>=3.5.0; extra == 'sync'
Provides-Extra: test
Requires-Dist: pytest-asyncio<0.24.0,>=0.23.7; extra == 'test'
Requires-Dist: pytest-mock<4.0.0,>=3.14.0; extra == 'test'
Requires-Dist: pytest-subtests<0.13.0,>=0.12.1; extra == 'test'
Requires-Dist: pytest<9.0.0,>=8.2.0; extra == 'test'
